httptesting/__init__.py
httptesting/case/__init__.py
httptesting/case/conftest.py
httptesting/case/extfunc.py
httptesting/case/pytest.ini
httptesting/case/temp.txt
httptesting/case/test_load_case.py
httptesting/config/config.yaml
httptesting/library/__init__.py
httptesting/library/assert_case.py
httptesting/library/case.py
httptesting/library/case_queue.py
httptesting/library/config.py
httptesting/library/emailstmp.py
httptesting/library/falsework.py
httptesting/library/func.py
httptesting/library/gl.py
httptesting/library/har.py
httptesting/library/http.py
httptesting/library/Multipart.py
httptesting/library/parse.py
httptesting/library/scripts.py
httptesting/main.py
httptesting/template/template.yaml
LICENSE
httptesting-1.2.30.dist-info/entry_points.txt
httptesting-1.2.30.dist-info/LICENSE
httptesting-1.2.30.dist-info/WHEEL
httptesting-1.2.30.dist-info/METADATA
httptesting-1.2.30.dist-info/RECORD
