Metadata-Version: 2.1
Name: httptesting
Version: 1.2.30
Summary: Httptesting HTTP(s) interface testing framework.
Home-page: https://github.com/HttpTesting/pyhttp
License: Apache-2.0
Keywords: http,api,test,requests
Author: 天枢
Author-email: lengyaohui@163.com
Requires-Python: >=3.5,<4.0
Classifier: Development Status :: 3 - Alpha
Classifier: Environment :: Console
Classifier: Framework :: Pytest
Classifier: License :: OSI Approved :: Apache Software License
Classifier: Operating System :: Microsoft :: Windows
Classifier: Programming Language :: Python :: 3
Classifier: Programming Language :: Python :: 3.5
Classifier: Programming Language :: Python :: 3.6
Classifier: Programming Language :: Python :: 3.7
Classifier: Programming Language :: Python :: 3.8
Classifier: Programming Language :: Python :: 3.9
Classifier: Topic :: Software Development :: Documentation
Classifier: Topic :: Software Development :: Libraries :: Python Modules
Requires-Dist: colorama (==0.4.1)
Requires-Dist: pytest (==5.0.1)
Requires-Dist: pytest-html (==1.21.1)
Requires-Dist: pytest-repeat (==0.8.0)
Requires-Dist: pytest-rerunfailures (==7.0)
Requires-Dist: pytest-xdist (==1.29.0)
Requires-Dist: pyyaml (==5.1.1)
Requires-Dist: requests (==2.22.0)
Requires-Dist: requests-toolbelt (==0.9.1)
Requires-Dist: ruamel.yaml (==0.16.5)
Project-URL: Repository, https://github.com/HttpTesting/pyhttp
